pyrate_limiter/__init__.py
pyrate_limiter/abstracts/__init__.py
pyrate_limiter/abstracts/bucket.py
pyrate_limiter/abstracts/clock.py
pyrate_limiter/abstracts/rate.py
pyrate_limiter/abstracts/wrappers.py
pyrate_limiter/buckets/__init__.py
pyrate_limiter/buckets/in_memory_bucket.py
pyrate_limiter/buckets/postgres.py
pyrate_limiter/buckets/redis_bucket.py
pyrate_limiter/buckets/sqlite_bucket.py
pyrate_limiter/clocks.py
pyrate_limiter/exceptions.py
pyrate_limiter/limiter.py
pyrate_limiter/py.typed
pyrate_limiter/utils.py
pyrate_limiter-3.7.1.dist-info/LICENSE
pyrate_limiter-3.7.1.dist-info/METADATA
pyrate_limiter-3.7.1.dist-info/WHEEL
pyrate_limiter-3.7.1.dist-info/RECORD
