Metadata-Version: 2.1
Name: pyrate-limiter
Version: 3.7.1
Summary: Python Rate-Limiter using Leaky-Bucket Algorithm
Home-page: https://github.com/vutran1710/PyrateLimiter
License: MIT
Keywords: rate,rate-limiter,rate_limiter,ratelimiter,leaky-bucket,ratelimit,ratelimiting
Author: vutr
Author-email: me@vutr.io
Requires-Python: >=3.8,<4.0
Classifier: Development Status :: 5 - Production/Stable
Classifier: License :: OSI Approved :: MIT License
Classifier: Operating System :: OS Independent
Classifier: Programming Language :: Python :: 3
Classifier: Programming Language :: Python :: 3.8
Classifier: Programming Language :: Python :: 3.9
Classifier: Programming Language :: Python :: 3.10
Classifier: Programming Language :: Python :: 3.11
Classifier: Programming Language :: Python :: 3.12
Classifier: Programming Language :: Python :: 3.13
Classifier: Topic :: Software Development :: Documentation
Classifier: Topic :: Software Development :: Libraries :: Python Modules
Classifier: Typing :: Typed
Provides-Extra: all
Provides-Extra: docs
Requires-Dist: filelock (>=3.0) ; extra == "all"
Requires-Dist: furo (>=2022.3.4,<2023.0.0) ; extra == "docs"
Requires-Dist: myst-parser (>=0.17) ; extra == "docs"
Requires-Dist: psycopg[pool] (>=3.1.18,<4.0.0) ; extra == "all"
Requires-Dist: redis (>=5.0.0,<6.0.0) ; extra == "all"
Requires-Dist: sphinx (>=4.3.0,<5.0.0) ; extra == "docs"
Requires-Dist: sphinx-autodoc-typehints (>=1.17,<2.0) ; extra == "docs"
Requires-Dist: sphinx-copybutton (>=0.5) ; extra == "docs"
Requires-Dist: sphinxcontrib-apidoc (>=0.3,<0.4) ; extra == "docs"
Project-URL: Documentation, https://pyrate-limiter.readthedocs.io
Project-URL: Repository, https://github.com/vutran1710/PyrateLimiter
